fairdomseek/__init__.py
fairdomseek/app_context.py
fairdomseekclient-0.1.0.dist-info/METADATA
fairdomseekclient-0.1.0.dist-info/WHEEL
fairdomseekclient-0.1.0.dist-info/top_level.txt
fairdomseekclient-0.1.0.dist-info/RECORD
