Metadata-Version: 2.4
Name: fairdomseekclient
Version: 0.1.0
Summary: A python client for fairdomseek platform
Author-email: Pascal Le Metayer <pascal.lemetayer@irt-saintexupery.com>
License-Expression: MIT
Requires-Python: >=3.11
Requires-Dist: requests>=2.25.1
Requires-Dist: fairdomseek-openapi-client==1.0.0
Provides-Extra: dev
Requires-Dist: pytest; extra == "dev"
Requires-Dist: black; extra == "dev"
Requires-Dist: mypy; extra == "dev"
Requires-Dist: isort; extra == "dev"
